feed_to_sqlite/__init__.py
feed_to_sqlite/cli.py
feed_to_sqlite/ingest.py
feed_to_sqlite-0.6.2.dist-info/WHEEL
feed_to_sqlite-0.6.2.dist-info/entry_points.txt
feed_to_sqlite-0.6.2.dist-info/METADATA
feed_to_sqlite-0.6.2.dist-info/RECORD
