Metadata-Version: 2.4
Name: feed-to-sqlite
Version: 0.6.2
Summary: Save an RSS or ATOM feed to a SQLITE database
Author: Chris Amico
Author-email: Chris Amico <eyeseast@gmail.com>
License-Expression: Apache-2.0
Classifier: Development Status :: 3 - Alpha
Classifier: Intended Audience :: Developers
Classifier: Intended Audience :: End Users/Desktop
Classifier: License :: OSI Approved :: Apache Software License
Classifier: Topic :: Database
Classifier: Programming Language :: Python :: 3.9
Classifier: Programming Language :: Python :: 3.10
Classifier: Programming Language :: Python :: 3.11
Classifier: Programming Language :: Python :: 3.12
Classifier: Programming Language :: Python :: 3.13
Requires-Dist: sqlite-utils>=2.22
Requires-Dist: httpx
Requires-Dist: feedparser
Requires-Dist: awesome-slugify
Requires-Python: >=3.9
Project-URL: homepage, https://github.com/eyeseast/feed-to-sqlite
Project-URL: source, https://github.com/eyeseast/feed-to-sqlite
